modo2auth/__init__.py
modo2auth-1.2.1.dist-info/LICENSE
modo2auth-1.2.1.dist-info/METADATA
modo2auth-1.2.1.dist-info/WHEEL
modo2auth-1.2.1.dist-info/top_level.txt
modo2auth-1.2.1.dist-info/RECORD
