Metadata-Version: 2.1
Name: modo2auth
Version: 1.2.1
Summary: Generate Modo Authentication
Home-page: https://github.com/modopayments-ux/modo2auth-py
License: UNKNOWN
Platform: UNKNOWN
